clv/__init__.py
clv/app.py
clv/utils.py
clv/api/__init__.py
clv/api/crud.py
clv/api/fast.py
clv/db/__init__.py
clv/db/data_generator.py
clv/db/schema.py
clv/db/sql_interactions.py
clv/logger/__init__.py
clv/logger/logger.py
clv/models/CLV.py
clv/models/Data_Processing.py
clv/models/__init__.py
SocraCLV-0.9.9.dist-info/LICENSE
SocraCLV-0.9.9.dist-info/METADATA
SocraCLV-0.9.9.dist-info/WHEEL
SocraCLV-0.9.9.dist-info/top_level.txt
SocraCLV-0.9.9.dist-info/RECORD
