Metadata-Version: 2.1
Name: SocraCLV
Version: 0.9.9
Summary: CLV prediction
Home-page: https://github.com/yeranosyanvahan/ma_group_project
Author: Group 5
License-File: LICENSE
